AUTHORS.rst
CONTRIBUTING.rst
HISTORY.rst
LICENSE
MANIFEST.in
README.rst
setup.cfg
setup.py
crcnsget/__init__.py
crcnsget/cli.py
crcnsget/crcnsget.py
crcnsget.egg-info/PKG-INFO
crcnsget.egg-info/SOURCES.txt
crcnsget.egg-info/dependency_links.txt
crcnsget.egg-info/entry_points.txt
crcnsget.egg-info/not-zip-safe
crcnsget.egg-info/requires.txt
crcnsget.egg-info/top_level.txt
docs/Makefile
docs/authors.rst
docs/conf.py
docs/contributing.rst
docs/history.rst
docs/index.rst
docs/installation.rst
docs/make.bat
docs/readme.rst
docs/usage.rst
tests/__init__.py
tests/test_crcnsget.py