Metadata-Version: 1.1
Name: crcnsget
Version: 0.1.0
Summary: Command-line interface for downloading data from crcns.org
Home-page: https://github.com/neuromusic/crcnsget
Author: Justin Kiggins
Author-email: justin.kiggins@gmail.com
License: BSD license
Keywords: crcnsget
Platform: UNKNOWN
Classifier: Development Status :: 2 - Pre-Alpha
Classifier: Intended Audience :: Developers
Classifier: License :: OSI Approved :: BSD License
Classifier: Natural Language :: English
Classifier: Programming Language :: Python :: 2
Classifier: Programming Language :: Python :: 2.6
Classifier: Programming Language :: Python :: 2.7
